bytedmetacenter/__init__.py
bytedmetacenter-0.0.1.dist-info/METADATA
bytedmetacenter-0.0.1.dist-info/WHEEL
bytedmetacenter-0.0.1.dist-info/top_level.txt
bytedmetacenter-0.0.1.dist-info/RECORD
